{"canvas": [{"name": "Carla", "pos1x": 1550.0, "pos1y": 784.0, "pos2x": 0.0, "pos2y": 0.0, "split": false}, {"name": "system", "pos1x": 1193.0, "pos1y": 1322.0, "pos2x": 1938.0, "pos2y": 1027.0, "split": true}, {"name": "Non-Mixer (Main)", "pos1x": 1410.0, "pos1y": 1040.0, "pos2x": 0.0, "pos2y": 0.0, "split": false}, {"name": "Non-Mixer (Other)", "pos1x": 1686.0, "pos1y": 1221.0, "pos2x": 0.0, "pos2y": 0.0, "split": false}, {"name": "Non-Mixer/Master", "pos1x": 1736.0, "pos1y": 1064.0, "pos2x": 0.0, "pos2y": 0.0, "split": false}, {"name": "voip", "pos1x": 1222.0, "pos1y": 1170.0, "pos2x": 0.0, "pos2y": 0.0, "split": false}, {"name": "media", "pos1x": 1218.0, "pos1y": 1014.0, "pos2x": 0.0, "pos2y": 0.0, "split": false}, {"name": "game", "pos1x": 1216.0, "pos1y": 1093.0, "pos2x": 0.0, "pos2y": 0.0, "split": false}, {"name": "masterCap", "pos1x": 1955.0, "pos1y": 1179.0, "pos2x": 0.0, "pos2y": 0.0, "split": false}, {"name": "micCap", "pos1x": 1688.0, "pos1y": 1302.0, "pos2x": 0.0, "pos2y": 0.0, "split": false}, {"name": "a2j", "pos1x": 1219.0, "pos1y": 898.0, "pos2x": 1618.0, "pos2y": 911.0, "split": true}]}